uiua-0.1.0.dist-info/METADATA
uiua-0.1.0.dist-info/WHEEL
uiua-0.1.0.dist-info/licenses/LICENSE
uiua/__init__.py
uiua/lib.cpython-313-x86_64-linux-gnu.so
uiua/lib.pyi
uiua/py.typed
uiua-0.1.0.dist-info/RECORD
