Metadata-Version: 2.4
Name: uiua
Version: 0.1.0
License-File: LICENSE
Summary: Python bindings for the Uiua array programming language
Author-email: Jiří Klimeš <jiri@klimes.dev>
Requires-Python: >=3.13
